{
  "schemaVersion": 1,
  "id": "south-australia",
  "name": "South Australia",
  "description": "Capstan shanty in C minor with bold, adventurous character",
  "defaults": {
    "bpm": 115,
    "key": "Cm"
  },
  "keyOffsets": {
    "Cm": 0,
    "Dm": 2,
    "Eb": 3,
    "Em": 4,
    "Fm": 5,
    "Gm": 7,
    "Ab": 8
  },
  "baseNotesHz": {
    "C2": 61.74,
    "D2": 69.3,
    "Eb2": 73.41,
    "E2": 77.78,
    "F2": 82.41,
    "G2": 92.5,
    "Ab2": 98.0,
    "A2": 103.83,
    "Bb2": 110.0,
    "B2": 116.54,
    "C3": 123.47,
    "D3": 138.59,
    "Eb3": 146.83,
    "E3": 155.56,
    "F3": 164.81,
    "G3": 185.0,
    "Ab3": 196.0,
    "A3": 207.65,
    "Bb3": 220.0,
    "B3": 233.08,
    "C4": 246.95,
    "D4": 277.18,
    "Eb4": 293.67,
    "F4": 329.63,
    "G4": 370.0,
    "G1": 46.25
  },
  "chordVoicings": {
    "Cm": {
      "label": "C minor",
      "notes": [
        "C2",
        "G2",
        "Eb3",
        "C4"
      ]
    },
    "Gm": {
      "label": "G minor",
      "notes": [
        "G2",
        "D3",
        "Bb3",
        "G4"
      ]
    },
    "Fm": {
      "label": "F minor",
      "notes": [
        "F2",
        "C3",
        "Ab3",
        "F4"
      ]
    },
    "Eb": {
      "label": "Eb major",
      "notes": [
        "Eb3",
        "Bb3",
        "G4",
        "Eb4"
      ]
    }
  },
  "droneVoicings": [
    {
      "root": "C2",
      "fifth": "G2"
    },
    {
      "root": "G2",
      "fifth": "D3"
    },
    {
      "root": "F2",
      "fifth": "C3"
    }
  ],
  "velocities": [
    0.92,
    0.7,
    0.86,
    0.9,
    0.74,
    0.94,
    0.72,
    0.88,
    0.93,
    0.77,
    0.84,
    0.91,
    0.79,
    0.89,
    0.95,
    0.81
  ],
  "layerIds": [
    "arp",
    "thump",
    "piano",
    "pad",
    "bass",
    "drone",
    "voiceBass",
    "voiceBaritone",
    "voiceTenor"
  ],
  "layerMix": {
    "arp": 0.5,
    "thump": 0.333,
    "piano": 0.3,
    "pad": 0.333,
    "bass": 0.333,
    "drone": 0.333,
    "voiceBass": 0.333,
    "voiceBaritone": 0.333,
    "voiceTenor": 0.333
  },
  "layerConfigs": {
    "arp": {
      "stepsPerBar": 16,
      "lfoHz": 4.6,
      "attackSec": 0.022,
      "decayTauMul": 0.9,
      "gainScale": 0.42
    },
    "thump": {
      "durationSec": 0.52,
      "startHz": 96,
      "endHz": 42,
      "pitchDecay": 5,
      "ampDecay": 4,
      "gainScale": 0.6
    },
    "piano": {
      "harmonics": [
        1,
        2,
        3
      ],
      "durationSec": 1.9,
      "voiceDelaySec": 0.008,
      "gainScale": 0.48
    },
    "pad": {
      "vibratoHz": 3.6,
      "vibratoDepth": 1.8,
      "lpfHz": 430,
      "voiceGain": 0.12,
      "gainScale": 0.28
    },
    "bass": {
      "lpfHz": 310,
      "hpfHz": 40,
      "detuneCents": -7,
      "gainScale": 0.28
    },
    "drone": {
      "holdBeats": 16,
      "pulseBeats": 16,
      "lpfHz": 240,
      "gainScale": 0.24
    },
    "voices": {
      "releaseSec": 2.8,
      "vibratoHz": 3.5,
      "formantHz": 710,
      "triggerSteps": [
        0,
        8
      ]
    }
  },
  "arpPattern": [
    "C3",
    "-",
    "C3",
    "-",
    "Eb3",
    "-",
    "G3",
    "-",
    "G3",
    "-",
    "Eb3",
    "-",
    "C3",
    "-",
    "G2",
    "-",
    "C3",
    "-",
    "Eb3",
    "-",
    "G3",
    "-",
    "C4",
    "-",
    "G3",
    "-",
    "Eb3",
    "-",
    "C3",
    "-",
    "G2",
    "-"
  ],
  "phaseFilterHz": {
    "phase1": 1396,
    "phase2": 1446,
    "phase3": 1494,
    "phase4": 1568,
    "phase5": 1348,
    "phase6": 1617,
    "phase7": 1421
  },
  "phases": [
    {
      "id": "phase1",
      "label": "Bound Away",
      "durationBeats": 32,
      "chordSeq": [
        "Cm",
        "Gm",
        "Fm",
        "Cm",
        "Gm",
        "Fm",
        "Cm",
        "Gm"
      ],
      "droneMode": false,
      "arpPattern": [
        "C3",
        "-",
        "-",
        "-",
        "C3",
        "-",
        "-",
        "-",
        "Eb3",
        "-",
        "-",
        "-",
        "G3",
        "-",
        "-",
        "-",
        "G3",
        "-",
        "-",
        "-",
        "Eb3",
        "-",
        "-",
        "-",
        "C3",
        "-",
        "-",
        "-",
        "G2",
        "-",
        "-",
        "-"
      ],
      "lv": {
        "arp": 0.352,
        "thump": 0.235,
        "piano": 0.211,
        "pad": 0.235,
        "bass": 0.235,
        "drone": 0.235,
        "voiceBass": 0.235,
        "voiceBaritone": 0.235,
        "voiceTenor": 0.235
      }
    },
    {
      "id": "phase2",
      "label": "Southern Cross",
      "durationBeats": 32,
      "chordSeq": [
        "Cm",
        "Fm",
        "Gm",
        "Cm",
        "Gm",
        "Cm",
        "Fm",
        "Cm"
      ],
      "droneMode": false,
      "arpPattern": [
        "C3",
        "-",
        "Eb3",
        "-",
        "G3",
        "-",
        "-",
        "-",
        "Eb3",
        "-",
        "C3",
        "-",
        "G2",
        "-",
        "-",
        "-",
        "C4",
        "-",
        "G3",
        "-",
        "Eb3",
        "-",
        "-",
        "-",
        "G3",
        "-",
        "Eb3",
        "-",
        "C3",
        "-",
        "-",
        "-"
      ],
      "lv": {
        "arp": 0.399,
        "thump": 0.266,
        "piano": 0.239,
        "pad": 0.266,
        "bass": 0.266,
        "drone": 0.266,
        "voiceBass": 0.266,
        "voiceBaritone": 0.266,
        "voiceTenor": 0.266
      }
    },
    {
      "id": "phase3",
      "label": "Open Ocean",
      "durationBeats": 48,
      "chordSeq": [
        "Cm",
        "Gm",
        "Fm",
        "Cm",
        "Gm",
        "Fm",
        "Eb",
        "Cm",
        "Gm",
        "Fm",
        "Cm",
        "Gm"
      ],
      "droneMode": false,
      "arpPattern": [
        "C3",
        "-",
        "Eb3",
        "-",
        "G3",
        "-",
        "C4",
        "-",
        "G3",
        "-",
        "Eb3",
        "-",
        "C3",
        "-",
        "G2",
        "-",
        "C3",
        "-",
        "Eb3",
        "-",
        "G3",
        "-",
        "Eb4",
        "-",
        "C4",
        "-",
        "G3",
        "-",
        "Eb3",
        "-",
        "C3",
        "-",
        "G2",
        "-",
        "C3",
        "-",
        "Eb3",
        "-",
        "G3",
        "-",
        "C4",
        "-",
        "G3",
        "-",
        "Eb3",
        "-",
        "C3",
        "-"
      ],
      "lv": {
        "arp": 0.452,
        "thump": 0.301,
        "piano": 0.271,
        "pad": 0.301,
        "bass": 0.301,
        "drone": 0.301,
        "voiceBass": 0.301,
        "voiceBaritone": 0.301,
        "voiceTenor": 0.301
      }
    },
    {
      "id": "phase4",
      "label": "Cape of Storms",
      "durationBeats": 48,
      "chordSeq": [
        "Cm",
        "Fm",
        "Gm",
        "Cm",
        "Cm",
        "Fm",
        "Gm",
        "Cm",
        "Gm",
        "Cm",
        "Fm",
        "Gm"
      ],
      "droneMode": true,
      "arpPattern": [
        "C4",
        "-",
        "G3",
        "-",
        "Eb4",
        "-",
        "C4",
        "-",
        "G3",
        "-",
        "Eb3",
        "-",
        "G3",
        "-",
        "C4",
        "-",
        "Eb4",
        "-",
        "C4",
        "-",
        "G3",
        "-",
        "Eb3",
        "-",
        "C3",
        "-",
        "Eb3",
        "-",
        "G3",
        "-",
        "C4",
        "-",
        "G4",
        "-",
        "Eb4",
        "-",
        "C4",
        "-",
        "G3",
        "-",
        "Eb3",
        "-",
        "C3",
        "-",
        "G3",
        "-",
        "Eb3",
        "-",
        "C4",
        "-",
        "G3",
        "-",
        "Eb4",
        "-",
        "C4",
        "-",
        "G3",
        "-",
        "Eb3",
        "-",
        "C3",
        "-",
        "G2",
        "-"
      ],
      "lv": {
        "arp": 0.5,
        "thump": 0.333,
        "piano": 0.3,
        "pad": 0.333,
        "bass": 0.333,
        "drone": 0.333,
        "voiceBass": 0.333,
        "voiceBaritone": 0.333,
        "voiceTenor": 0.333
      }
    },
    {
      "id": "phase5",
      "label": "Doldrums",
      "durationBeats": 32,
      "chordSeq": [
        "Cm",
        "Gm",
        "Fm",
        "Cm",
        "Fm",
        "Gm",
        "Cm",
        "Gm"
      ],
      "droneMode": false,
      "arpPattern": [
        "C3",
        "-",
        "-",
        "-",
        "-",
        "-",
        "-",
        "-",
        "Eb3",
        "-",
        "-",
        "-",
        "-",
        "-",
        "-",
        "-",
        "G3",
        "-",
        "-",
        "-",
        "-",
        "-",
        "-",
        "-",
        "C3",
        "-",
        "-",
        "-",
        "-",
        "-",
        "-",
        "-"
      ],
      "lv": {
        "arp": 0.452,
        "thump": 0.301,
        "piano": 0.271,
        "pad": 0.301,
        "bass": 0.301,
        "drone": 0.301,
        "voiceBass": 0.301,
        "voiceBaritone": 0.301,
        "voiceTenor": 0.301
      }
    },
    {
      "id": "phase6",
      "label": "Fair Winds!",
      "durationBeats": 48,
      "chordSeq": [
        "Cm",
        "Gm",
        "Fm",
        "Cm",
        "Fm",
        "Gm",
        "Eb",
        "Cm",
        "Gm",
        "Fm",
        "Cm",
        "Gm"
      ],
      "droneMode": true,
      "arpPattern": [
        "G3",
        "-",
        "C4",
        "-",
        "Eb4",
        "-",
        "C4",
        "-",
        "G3",
        "-",
        "Eb3",
        "-",
        "C3",
        "-",
        "Eb3",
        "-",
        "G3",
        "-",
        "C4",
        "-",
        "G4",
        "-",
        "C4",
        "-",
        "G3",
        "-",
        "Eb3",
        "-",
        "G3",
        "-",
        "C4",
        "-",
        "Eb4",
        "-",
        "C4",
        "-",
        "G3",
        "-",
        "Eb3",
        "-",
        "C3",
        "-",
        "G2",
        "-",
        "C3",
        "-",
        "Eb3",
        "-"
      ],
      "lv": {
        "arp": 0.399,
        "thump": 0.266,
        "piano": 0.239,
        "pad": 0.266,
        "bass": 0.266,
        "drone": 0.266,
        "voiceBass": 0.266,
        "voiceBaritone": 0.266,
        "voiceTenor": 0.266
      }
    },
    {
      "id": "phase7",
      "label": "Adelaide",
      "durationBeats": 32,
      "chordSeq": [
        "Cm",
        "Fm",
        "Gm",
        "Cm",
        "Gm",
        "Fm",
        "Cm",
        "Eb"
      ],
      "droneMode": false,
      "arpPattern": [
        "C3",
        "-",
        "-",
        "-",
        "-",
        "-",
        "-",
        "-",
        "Eb3",
        "-",
        "-",
        "-",
        "G3",
        "-",
        "-",
        "-",
        "G3",
        "-",
        "-",
        "-",
        "Eb3",
        "-",
        "-",
        "-",
        "C3",
        "-",
        "-",
        "-",
        "-",
        "-",
        "-",
        "-"
      ],
      "lv": {
        "arp": 0.352,
        "thump": 0.235,
        "piano": 0.211,
        "pad": 0.235,
        "bass": 0.235,
        "drone": 0.235,
        "voiceBass": 0.235,
        "voiceBaritone": 0.235,
        "voiceTenor": 0.235
      }
    }
  ]
}
